README.md
setup.py
onnmisc/__init__.py
onnmisc.egg-info/PKG-INFO
onnmisc.egg-info/SOURCES.txt
onnmisc.egg-info/dependency_links.txt
onnmisc.egg-info/top_level.txt
onnmisc/aws/__init__.py
onnmisc/aws/cfn.py
onnmisc/aws/secrets_manager.py
onnmisc/transformers/__init__.py
onnmisc/transformers/b64.py
onnmisc/transformers/csv.py