Metadata-Version: 2.1
Name: onnmisc
Version: 0.0.10
Summary: Miscellaneous functions used to fulfill common requirements
Home-page: https://onnmisc.oznetnerd.com
Author: Will Robinson
Author-email: will@oznetnerd.com
License: UNKNOWN
Platform: UNKNOWN
